htmf/__init__.py
htmf/py.typed
htmf-0.3.0.dist-info/LICENSE
htmf-0.3.0.dist-info/WHEEL
htmf-0.3.0.dist-info/METADATA
htmf-0.3.0.dist-info/RECORD
