Metadata-Version: 2.1
Name: htmf
Version: 0.3.0
Summary: htmf: Python f-strings HTML templating library
Author: jkmnt
Requires-Python: >=3.8
Classifier: Programming Language :: Python :: 3
Classifier: License :: OSI Approved :: MIT License
Classifier: Operating System :: OS Independent
Project-URL: Documentation, https://jkmnt.github.com/htmf
Project-URL: Source, https://github.com/jkmnt/htmf
